{
  "date": "2026-04-24",
  "review_time": "2026-04-27T07:00:00+08:00",
  "market_summary": {
    "news": [
      "伊朗局势升温，中东地缘政治风险加剧",
      "美联储FOMC会议在即，利率政策预期成焦点",
      "科技股强势反弹，AI与半导体板块领涨",
      "财报季持续，科技巨头财报表现分化",
      "市场防御性转向，资金流向防御板块"
    ],
    "indices": [
      {"name": "道琼斯工业", "close": 49230.71, "change_pct": -0.16, "change_pts": -79.61},
      {"name": "标普500", "close": 7165.08, "change_pct": 0.80, "change_pts": 56.68},
      {"name": "纳斯达克综指", "close": 24836.60, "change_pct": 1.63, "change_pts": 398.09},
      {"name": "罗素2000", "close": 2787.00, "change_pct": 0.43, "change_pts": 11.90},
      {"name": "VIX恐慌指数", "close": 18.71, "change_pct": -3.11, "change_pts": -0.60}
    ],
    "sentiment": "mixed"
  },
  "portfolio_review": {
    "positions_count": 0,
    "portfolio_value": 0,
    "total_pnl": 0,
    "total_pnl_rate": 0
  },
  "stock_pool": {
    "value_count": 30,
    "growth_count": 30,
    "tech_count": 0,
    "momentum_count": 20,
    "total_unique": 80,
    "data_quality": "poor - all financial metrics are 0"
  },
  "trading_plan": [
    "市场震荡，保持观望",
    "等待美联储会议结果后再做方向性决策",
    "关注伊朗局势对能源板块的影响",
    "修复股票池数据源问题"
  ],
  "risks": [
    "中东地缘政治风险可能突然升级",
    "美联储政策超预期可能引发市场剧烈波动",
    "科技股估值偏高，存在回调风险",
    "美股组合尚未建仓"
  ]
}
